{"graph_1": [[0, 1], [1, 0], [1, 2], [2, 1], [0, 3], [3, 0], [3, 4], [4, 3], [4, 5], [5, 4], [0, 6], [6, 0], [6, 7], [7, 6], [7, 8], [8, 7]], "graph_2": [[0, 1], [1, 0], [0, 4], [4, 0], [1, 2], [2, 1], [2, 3], [3, 2], [2, 5], [5, 2], [3, 4], [4, 3], [4, 14], [14, 4], [5, 6], [6, 5], [5, 9], [9, 5], [6, 7], [7, 6], [7, 8], [8, 7], [7, 13], [13, 7], [8, 11], [11, 8], [8, 12], [12, 8], [9, 10], [10, 9], [9, 11], [11, 9], [14, 15], [15, 14], [15, 16], [16, 15], [16, 17], [17, 16], [16, 23], [23, 16], [16, 24], [24, 16], [18, 19], [19, 18], [18, 23], [23, 18], [19, 20], [20, 19], [19, 26], [26, 19], [21, 22], [22, 21], [21, 24], [24, 21], [22, 25], [25, 22], [22, 30], [30, 22], [26, 27], [27, 26], [26, 28], [28, 26], [26, 29], [29, 26], [30, 31], [31, 30], [30, 32], [32, 30], [30, 33], [33, 30]], "labels_1": [0, 0, 2, 2, 0, 0, 2, 0, 0], "labels_2": [0, 0, 0, 1, 0, 2, 0, 0, 0, 0, 1, 2, 1, 0, 0, 1, 7, 1, 0, 0, 1, 0, 0, 1, 1, 1, 0, 0, 0, 0, 0, 0, 0, 0], "ged": 22}